{"AIF":{"nodes":[{"nodeID":"2_174349664410634128","text":"to Carmen Maria Rojas, as thanks for her steadfast service, and honest friendship, Nick leaves the remainder of his estate, including Old Scratch Tavern, and all associated assets","type":"I"},{"nodeID":"3_174349664410634128","text":"Nick's Will: To Carmen Maria Rojas, as thanks for her steadfast service, and honest friendship, I leave the remainder of my estate, including Old Scratch Tavern, and all associated assets","type":"L"},{"nodeID":"4_174349664410634128","text":"Analysing","type":"YA"},{"nodeID":"5_174349664410634128","text":"Anon: Nick's Will: To Carmen Maria Rojas, as thanks for her steadfast service, and honest friendship, I leave the remainder of my estate, including Old Scratch Tavern, and all associated assets","type":"L"},{"nodeID":"6_174349664410634128","text":"Asserting","type":"YA"},{"nodeID":"7_174349664410634128","text":"Participant 28: To Carmen Maria Rojas, as thanks for her steadfast service, and honest friendship, I leave the remainder of my estate, including Old Scratch Tavern, and all associated assets","type":"L"},{"nodeID":"8_174349664410634128","text":"Analysing","type":"YA"},{"nodeID":"9_174349664410634128","text":"Anon: Participant 28: Nick's Will: To Carmen Maria Rojas, as thanks for her steadfast service, and honest friendship, I leave the remainder of my estate, including Old Scratch Tavern, and all associated assets","type":"L"},{"nodeID":"10_174349664410634128","text":"Asserting","type":"YA"},{"nodeID":"11_174349664410634128","text":"Carmen doesn't know Nick left her the Old Scratch Tavern","type":"I"},{"nodeID":"12_174349664410634128","text":"Participant 28: Carmen doesn't know","type":"L"},{"nodeID":"13_174349664410634128","text":"Analysing","type":"YA"},{"nodeID":"14_174349664410634128","text":"Anon: Participant 28: Carmen doesn't know","type":"L"},{"nodeID":"15_174349664410634128","text":"Asserting","type":"YA"},{"nodeID":"16_174349664410634128","text":"Default Transition","type":"TA"},{"nodeID":"17_174349664410634128","text":"Carmen thinks that Cherie owns Old Scratch","type":"I"},{"nodeID":"18_174349664410634128","text":"Participant 28: Carmen thinks that Cherie owns Old Scratch","type":"L"},{"nodeID":"19_174349664410634128","text":"Analysing","type":"YA"},{"nodeID":"20_174349664410634128","text":"Anon: Participant 28: Carmen thinks that Cherie owns Old Scratch","type":"L"},{"nodeID":"21_174349664410634128","text":"Asserting","type":"YA"},{"nodeID":"22_174349664410634128","text":"Default Transition","type":"TA"},{"nodeID":"23_174349664410634128","text":"Default Rephrase","type":"MA"},{"nodeID":"24_174349664410634128","text":"Restating","type":"YA"},{"nodeID":"26_174349664410634128","text":"Participant 30: Yeah","type":"L"},{"nodeID":"27_174349664410634128","text":"Analysing","type":"YA"},{"nodeID":"28_174349664410634128","text":"Anon: Participant 30: Yeah","type":"L"},{"nodeID":"30_174349664410634128","text":"Default Transition","type":"TA"},{"nodeID":"31_174349664410634128","text":"Agreeing","type":"YA"},{"nodeID":"37_174349664410634128","text":"Nick has intentionally, and not as a result of any mistake, or inadvertence, omitted in his will to provide for his spouse Cherie Anne Webster","type":"I"},{"nodeID":"38_174349664410634128","text":"Nick's Will: I have intentionally, and not as a result of any mistake, or inadvertence, omitted in this will to provide for my spouse Cherie Anne Webster","type":"L"},{"nodeID":"39_174349664410634128","text":"Analysing","type":"YA"},{"nodeID":"40_174349664410634128","text":"Anon: Nick's Will: I have intentionally, and not as a result of any mistake, or inadvertence, omitted in this will to provide for my spouse Cherie Anne Webster","type":"L"},{"nodeID":"41_174349664410634128","text":"Asserting","type":"YA"},{"nodeID":"42_174349664410634128","text":"Participant 28: I have intentionally, and not as a result of any mistake, or inadvertence, omitted in this will to provide for my spouse Cherie Anne Webster","type":"L"},{"nodeID":"43_174349664410634128","text":"Analysing","type":"YA"},{"nodeID":"44_174349664410634128","text":"Anon: Participant 28: Nick's Will: I have intentionally, and not as a result of any mistake, or inadvertence, omitted in this will to provide for my spouse Cherie Anne Webster","type":"L"},{"nodeID":"45_174349664410634128","text":"Asserting","type":"YA"},{"nodeID":"46_174349664410634128","text":"Default Transition","type":"TA"},{"nodeID":"47_174349664410634128","text":"Nick had worked out that Cherie was having an affair","type":"I"},{"nodeID":"48_174349664410634128","text":"Participant 28: he'd worked out that she was having an affair","type":"L"},{"nodeID":"49_174349664410634128","text":"Analysing","type":"YA"},{"nodeID":"50_174349664410634128","text":"Anon: Participant 28: he'd worked out that she was having an affair","type":"L"},{"nodeID":"51_174349664410634128","text":"Asserting","type":"YA"},{"nodeID":"52_174349664410634128","text":"Default Inference","type":"RA"},{"nodeID":"53_174349664410634128","text":"Default Transition","type":"TA"},{"nodeID":"54_174349664410634128","text":"Arguing","type":"YA"},{"nodeID":"56_174349664410634128","text":"Participant 30: Yeah","type":"L"},{"nodeID":"57_174349664410634128","text":"Analysing","type":"YA"},{"nodeID":"58_174349664410634128","text":"Anon: Participant 30: Yeah","type":"L"},{"nodeID":"60_174349664410634128","text":"Default Transition","type":"TA"},{"nodeID":"61_174349664410634128","text":"Agreeing","type":"YA"}],"edges":[{"edgeID":1,"fromID":"4_174349664410634128","toID":"3_174349664410634128"},{"edgeID":2,"fromID":"5_174349664410634128","toID":"4_174349664410634128"},{"edgeID":3,"fromID":"3_174349664410634128","toID":"6_174349664410634128"},{"edgeID":4,"fromID":"6_174349664410634128","toID":"2_174349664410634128"},{"edgeID":5,"fromID":"8_174349664410634128","toID":"7_174349664410634128"},{"edgeID":6,"fromID":"9_174349664410634128","toID":"8_174349664410634128"},{"edgeID":7,"fromID":"7_174349664410634128","toID":"10_174349664410634128"},{"edgeID":8,"fromID":"10_174349664410634128","toID":"3_174349664410634128"},{"edgeID":9,"fromID":"13_174349664410634128","toID":"12_174349664410634128"},{"edgeID":10,"fromID":"14_174349664410634128","toID":"13_174349664410634128"},{"edgeID":11,"fromID":"12_174349664410634128","toID":"15_174349664410634128"},{"edgeID":12,"fromID":"15_174349664410634128","toID":"11_174349664410634128"},{"edgeID":13,"fromID":"7_174349664410634128","toID":"16_174349664410634128"},{"edgeID":14,"fromID":"16_174349664410634128","toID":"12_174349664410634128"},{"edgeID":15,"fromID":"19_174349664410634128","toID":"18_174349664410634128"},{"edgeID":16,"fromID":"20_174349664410634128","toID":"19_174349664410634128"},{"edgeID":17,"fromID":"18_174349664410634128","toID":"21_174349664410634128"},{"edgeID":18,"fromID":"21_174349664410634128","toID":"17_174349664410634128"},{"edgeID":19,"fromID":"12_174349664410634128","toID":"22_174349664410634128"},{"edgeID":20,"fromID":"22_174349664410634128","toID":"18_174349664410634128"},{"edgeID":21,"fromID":"17_174349664410634128","toID":"23_174349664410634128"},{"edgeID":22,"fromID":"23_174349664410634128","toID":"11_174349664410634128"},{"edgeID":23,"fromID":"22_174349664410634128","toID":"24_174349664410634128"},{"edgeID":24,"fromID":"24_174349664410634128","toID":"23_174349664410634128"},{"edgeID":25,"fromID":"27_174349664410634128","toID":"26_174349664410634128"},{"edgeID":26,"fromID":"28_174349664410634128","toID":"27_174349664410634128"},{"edgeID":27,"fromID":"18_174349664410634128","toID":"30_174349664410634128"},{"edgeID":28,"fromID":"30_174349664410634128","toID":"26_174349664410634128"},{"edgeID":29,"fromID":"30_174349664410634128","toID":"31_174349664410634128"},{"edgeID":30,"fromID":"31_174349664410634128","toID":"17_174349664410634128"},{"edgeID":31,"fromID":"39_174349664410634128","toID":"38_174349664410634128"},{"edgeID":32,"fromID":"40_174349664410634128","toID":"39_174349664410634128"},{"edgeID":33,"fromID":"38_174349664410634128","toID":"41_174349664410634128"},{"edgeID":34,"fromID":"41_174349664410634128","toID":"37_174349664410634128"},{"edgeID":35,"fromID":"43_174349664410634128","toID":"42_174349664410634128"},{"edgeID":36,"fromID":"44_174349664410634128","toID":"43_174349664410634128"},{"edgeID":37,"fromID":"42_174349664410634128","toID":"45_174349664410634128"},{"edgeID":38,"fromID":"45_174349664410634128","toID":"38_174349664410634128"},{"edgeID":39,"fromID":"7_174349664410634128","toID":"46_174349664410634128"},{"edgeID":40,"fromID":"46_174349664410634128","toID":"42_174349664410634128"},{"edgeID":41,"fromID":"49_174349664410634128","toID":"48_174349664410634128"},{"edgeID":42,"fromID":"50_174349664410634128","toID":"49_174349664410634128"},{"edgeID":43,"fromID":"48_174349664410634128","toID":"51_174349664410634128"},{"edgeID":44,"fromID":"51_174349664410634128","toID":"47_174349664410634128"},{"edgeID":45,"fromID":"37_174349664410634128","toID":"52_174349664410634128"},{"edgeID":46,"fromID":"52_174349664410634128","toID":"47_174349664410634128"},{"edgeID":47,"fromID":"42_174349664410634128","toID":"53_174349664410634128"},{"edgeID":48,"fromID":"53_174349664410634128","toID":"48_174349664410634128"},{"edgeID":49,"fromID":"53_174349664410634128","toID":"54_174349664410634128"},{"edgeID":50,"fromID":"54_174349664410634128","toID":"52_174349664410634128"},{"edgeID":51,"fromID":"57_174349664410634128","toID":"56_174349664410634128"},{"edgeID":52,"fromID":"58_174349664410634128","toID":"57_174349664410634128"},{"edgeID":53,"fromID":"48_174349664410634128","toID":"60_174349664410634128"},{"edgeID":54,"fromID":"60_174349664410634128","toID":"56_174349664410634128"},{"edgeID":55,"fromID":"60_174349664410634128","toID":"61_174349664410634128"},{"edgeID":56,"fromID":"61_174349664410634128","toID":"47_174349664410634128"}],"schemefulfillments":[{"nodeID":"4_174349664410634128","schemeID":"75"},{"nodeID":"6_174349664410634128","schemeID":"74"},{"nodeID":"8_174349664410634128","schemeID":"75"},{"nodeID":"10_174349664410634128","schemeID":"74"},{"nodeID":"13_174349664410634128","schemeID":"75"},{"nodeID":"15_174349664410634128","schemeID":"74"},{"nodeID":"16_174349664410634128","schemeID":"82"},{"nodeID":"19_174349664410634128","schemeID":"75"},{"nodeID":"21_174349664410634128","schemeID":"74"},{"nodeID":"22_174349664410634128","schemeID":"82"},{"nodeID":"23_174349664410634128","schemeID":"144"},{"nodeID":"24_174349664410634128","schemeID":"101"},{"nodeID":"27_174349664410634128","schemeID":"75"},{"nodeID":"30_174349664410634128","schemeID":"82"},{"nodeID":"31_174349664410634128","schemeID":"77"},{"nodeID":"39_174349664410634128","schemeID":"75"},{"nodeID":"41_174349664410634128","schemeID":"74"},{"nodeID":"43_174349664410634128","schemeID":"75"},{"nodeID":"45_174349664410634128","schemeID":"74"},{"nodeID":"46_174349664410634128","schemeID":"82"},{"nodeID":"49_174349664410634128","schemeID":"75"},{"nodeID":"51_174349664410634128","schemeID":"74"},{"nodeID":"52_174349664410634128","schemeID":"72"},{"nodeID":"53_174349664410634128","schemeID":"82"},{"nodeID":"54_174349664410634128","schemeID":"80"},{"nodeID":"57_174349664410634128","schemeID":"75"},{"nodeID":"60_174349664410634128","schemeID":"82"},{"nodeID":"61_174349664410634128","schemeID":"77"}],"participants":[{"participantID":1,"firstname":"Participant","surname":"Rachel"},{"participantID":2,"firstname":"Participant","surname":"Carolyn"},{"participantID":3,"firstname":"Participant","surname":"Mo"},{"participantID":4,"firstname":"Participant","surname":"Zoe"},{"participantID":5,"firstname":"Participant","surname":"Claire"},{"participantID":6,"firstname":"Participant","surname":"Lee"},{"participantID":7,"firstname":"Participant","surname":"Sally"},{"participantID":8,"firstname":"Participant","surname":"Kalbir"},{"participantID":9,"firstname":"Participant","surname":"Alice"},{"participantID":10,"firstname":"Anne","surname":"Robinson"},{"participantID":11,"firstname":"Diane","surname":"Munday"},{"participantID":12,"firstname":"Neena","surname":"Modi"},{"participantID":13,"firstname":"David","surname":"Steel"},{"participantID":14,"firstname":"Neil","surname":"Lyndon"},{"participantID":15,"firstname":"Participant","surname":"28"},{"participantID":16,"firstname":"Participant","surname":"30"},{"participantID":17,"firstname":"Participant","surname":"29"},{"participantID":18,"firstname":"Deputy","surname":"Notes"},{"participantID":19,"firstname":"Coaster","surname":"from Bar"},{"participantID":20,"firstname":"Nick's","surname":"Will"},{"participantID":21,"firstname":"Letter","surname":"to Cherie"},{"participantID":22,"firstname":"Emails","surname":"about Property"}],"locutions":[{"nodeID":"3_174349664410634128","personID":20,"start":null,"end":null},{"nodeID":"7_174349664410634128","personID":15,"start":"2025-09-09 12:51:53","end":null},{"nodeID":"12_174349664410634128","personID":15,"start":"2025-09-09 12:51:54","end":null},{"nodeID":"18_174349664410634128","personID":15,"start":"2025-09-09 12:51:55","end":null},{"nodeID":"26_174349664410634128","personID":16,"start":"2025-09-09 12:51:56","end":null},{"nodeID":"38_174349664410634128","personID":20,"start":null,"end":null},{"nodeID":"42_174349664410634128","personID":15,"start":"2025-09-09 12:52:50","end":null},{"nodeID":"48_174349664410634128","personID":15,"start":"2025-09-09 12:53:09","end":null},{"nodeID":"56_174349664410634128","personID":16,"start":"2025-09-09 12:53:11","end":null}],"descriptorfulfillments":[],"cqdescriptorfulfillments":[]},"text":"Part 28\n[2025/09/09 12:00:00 GMT+0000]&nbsp;<div>[00:51:33] Participant 28: I have always felt terrible that the driver who killed your Tom was leaving the Old Scratch, and I don't blame you for holding a grudge. I hope this helps to make things right, I should have done it sooner. For Donna Marie Goddard, in recognition of her years of loyal patronage, I provide that she receive free drinks at the Old Scratch Tavern for the period of her natural life, or for as long as the bar remains in business, whichever is longest. Should she fail to survive me, or for any reason refuses the bequest, it is not transferable to any other individual. You've supported me from the very start, and I want you to know, you'll always be welcome at Old Scratch. <span id=\"node3_174349664410634128\" class=\"highlighted\">To Carmen Maria Rojas, as thanks for her steadfast service, and honest friendship, I leave the remainder of my estate, including Old Scratch Tavern, and all associated assets</span>. But <span id=\"node12_174349664410634128\" class=\"highlighted\">Carmen doesn't know</span>. <span id=\"node18_174349664410634128\" class=\"highlighted\">Carmen thinks that Cherie owns Old Scratch</span>.\n[00:51:56] Participant 30: <span id=\"node26_174349664410634128\" class=\"highlighted\">Yeah</span>, oh no.&nbsp;</div><div>[00:51:56] Participant 28: As well as my retirement account, and the payout of my insurance policy.\n[00:51:56] Participant 30: Uh-oh.\n[00:51:56] Participant 28: Should she fail to survive me, or for any reason, refuses this bequest, [00:52:00] I then divide and bequeath the remainder of my estate to her sister, Christina. It's the least I can do for you, kiddo, you're the best, damn bartender in Indiana, and the kind of family I always hoped I'd find. I couldn't leave the bar in better hands. <span id=\"node38_174349664410634128\" class=\"highlighted\">I have intentionally, and not as a result of any mistake, or inadvertence, omitted in this will to provide for my spouse Cherie Anne Webster</span>. I know you never cared much for the [00:53:00] bar, but I thought at least you still cared for me. I was a fool to think so, but better a fool than a liar, I guess.\n[00:53:07] Participant 30: Yeah.\n[00:53:07] Participant 28: So, yeah, <span id=\"node48_174349664410634128\" class=\"highlighted\">he'd worked out that she was having an affair</span>.&nbsp;</div><div>[00:53:10] Participant 30: <span id=\"node56_174349664410634128\" class=\"highlighted\">Yeah</span>.</div>","OVA":{"firstname":"Anon","surname":"User","url":"","nodes":[{"nodeID":"2_174349664410634128","visible":true,"x":150,"y":60,"timestamp":""},{"nodeID":"3_174349664410634128","visible":true,"x":600,"y":60,"timestamp":""},{"nodeID":"4_174349664410634128","visible":false,"x":0,"y":0,"timestamp":""},{"nodeID":"5_174349664410634128","visible":false,"x":0,"y":0,"timestamp":""},{"nodeID":"6_174349664410634128","visible":true,"x":375,"y":60,"timestamp":""},{"nodeID":"7_174349664410634128","visible":true,"x":1050,"y":60,"timestamp":"Tue Sep 09 2025 13:51:53 GMT+0100"},{"nodeID":"8_174349664410634128","visible":false,"x":0,"y":0,"timestamp":""},{"nodeID":"9_174349664410634128","visible":false,"x":0,"y":0,"timestamp":""},{"nodeID":"10_174349664410634128","visible":true,"x":825,"y":60,"timestamp":""},{"nodeID":"11_174349664410634128","visible":true,"x":264,"y":262,"timestamp":""},{"nodeID":"12_174349664410634128","visible":true,"x":714,"y":262,"timestamp":"Tue Sep 09 2025 13:51:54 GMT+0100"},{"nodeID":"13_174349664410634128","visible":false,"x":0,"y":0,"timestamp":""},{"nodeID":"14_174349664410634128","visible":false,"x":0,"y":0,"timestamp":""},{"nodeID":"15_174349664410634128","visible":true,"x":489,"y":262,"timestamp":""},{"nodeID":"16_174349664410634128","visible":true,"x":881,"y":189,"timestamp":""},{"nodeID":"17_174349664410634128","visible":true,"x":261,"y":459,"timestamp":""},{"nodeID":"18_174349664410634128","visible":true,"x":711,"y":459,"timestamp":"Tue Sep 09 2025 13:51:55 GMT+0100"},{"nodeID":"19_174349664410634128","visible":false,"x":0,"y":0,"timestamp":""},{"nodeID":"20_174349664410634128","visible":false,"x":0,"y":0,"timestamp":""},{"nodeID":"21_174349664410634128","visible":true,"x":486,"y":459,"timestamp":""},{"nodeID":"22_174349664410634128","visible":true,"x":712,"y":375,"timestamp":""},{"nodeID":"23_174349664410634128","visible":true,"x":262,"y":378,"timestamp":""},{"nodeID":"24_174349664410634128","visible":true,"x":487,"y":387,"timestamp":""},{"nodeID":"26_174349664410634128","visible":true,"x":721,"y":622,"timestamp":"Tue Sep 09 2025 13:51:56 GMT+0100"},{"nodeID":"27_174349664410634128","visible":false,"x":0,"y":0,"timestamp":""},{"nodeID":"28_174349664410634128","visible":false,"x":0,"y":0,"timestamp":""},{"nodeID":"30_174349664410634128","visible":true,"x":715,"y":555,"timestamp":""},{"nodeID":"31_174349664410634128","visible":true,"x":487,"y":521,"timestamp":""},{"nodeID":"37_174349664410634128","visible":true,"x":262,"y":780,"timestamp":""},{"nodeID":"38_174349664410634128","visible":true,"x":712,"y":780,"timestamp":""},{"nodeID":"39_174349664410634128","visible":false,"x":0,"y":0,"timestamp":""},{"nodeID":"40_174349664410634128","visible":false,"x":0,"y":0,"timestamp":""},{"nodeID":"41_174349664410634128","visible":true,"x":487,"y":780,"timestamp":""},{"nodeID":"42_174349664410634128","visible":true,"x":1162,"y":780,"timestamp":"Tue Sep 09 2025 13:52:50 GMT+0100"},{"nodeID":"43_174349664410634128","visible":false,"x":0,"y":0,"timestamp":""},{"nodeID":"44_174349664410634128","visible":false,"x":0,"y":0,"timestamp":""},{"nodeID":"45_174349664410634128","visible":true,"x":937,"y":780,"timestamp":""},{"nodeID":"46_174349664410634128","visible":true,"x":1105,"y":462,"timestamp":""},{"nodeID":"47_174349664410634128","visible":true,"x":444,"y":1021,"timestamp":""},{"nodeID":"48_174349664410634128","visible":true,"x":894,"y":1021,"timestamp":"Tue Sep 09 2025 13:53:09 GMT+0100"},{"nodeID":"49_174349664410634128","visible":false,"x":0,"y":0,"timestamp":""},{"nodeID":"50_174349664410634128","visible":false,"x":0,"y":0,"timestamp":""},{"nodeID":"51_174349664410634128","visible":true,"x":669,"y":1021,"timestamp":""},{"nodeID":"52_174349664410634128","visible":true,"x":352,"y":929,"timestamp":""},{"nodeID":"53_174349664410634128","visible":true,"x":1027,"y":929,"timestamp":""},{"nodeID":"54_174349664410634128","visible":true,"x":680,"y":929,"timestamp":""},{"nodeID":"56_174349664410634128","visible":true,"x":914,"y":1183,"timestamp":"Tue Sep 09 2025 13:53:11 GMT+0100"},{"nodeID":"57_174349664410634128","visible":false,"x":0,"y":0,"timestamp":""},{"nodeID":"58_174349664410634128","visible":false,"x":0,"y":0,"timestamp":""},{"nodeID":"60_174349664410634128","visible":true,"x":903,"y":1116,"timestamp":""},{"nodeID":"61_174349664410634128","visible":true,"x":673,"y":1083,"timestamp":""}],"edges":[{"fromID":"4_174349664410634128","toID":"3_174349664410634128","visible":false},{"fromID":"5_174349664410634128","toID":"4_174349664410634128","visible":false},{"fromID":"3_174349664410634128","toID":"6_174349664410634128","visible":true},{"fromID":"6_174349664410634128","toID":"2_174349664410634128","visible":true},{"fromID":"8_174349664410634128","toID":"7_174349664410634128","visible":false},{"fromID":"9_174349664410634128","toID":"8_174349664410634128","visible":false},{"fromID":"7_174349664410634128","toID":"10_174349664410634128","visible":true},{"fromID":"10_174349664410634128","toID":"3_174349664410634128","visible":true},{"fromID":"13_174349664410634128","toID":"12_174349664410634128","visible":false},{"fromID":"14_174349664410634128","toID":"13_174349664410634128","visible":false},{"fromID":"12_174349664410634128","toID":"15_174349664410634128","visible":true},{"fromID":"15_174349664410634128","toID":"11_174349664410634128","visible":true},{"fromID":"7_174349664410634128","toID":"16_174349664410634128","visible":true},{"fromID":"16_174349664410634128","toID":"12_174349664410634128","visible":true},{"fromID":"19_174349664410634128","toID":"18_174349664410634128","visible":false},{"fromID":"20_174349664410634128","toID":"19_174349664410634128","visible":false},{"fromID":"18_174349664410634128","toID":"21_174349664410634128","visible":true},{"fromID":"21_174349664410634128","toID":"17_174349664410634128","visible":true},{"fromID":"12_174349664410634128","toID":"22_174349664410634128","visible":true},{"fromID":"22_174349664410634128","toID":"18_174349664410634128","visible":true},{"fromID":"17_174349664410634128","toID":"23_174349664410634128","visible":true},{"fromID":"23_174349664410634128","toID":"11_174349664410634128","visible":true},{"fromID":"22_174349664410634128","toID":"24_174349664410634128","visible":true},{"fromID":"24_174349664410634128","toID":"23_174349664410634128","visible":true},{"fromID":"27_174349664410634128","toID":"26_174349664410634128","visible":false},{"fromID":"28_174349664410634128","toID":"27_174349664410634128","visible":false},{"fromID":"18_174349664410634128","toID":"30_174349664410634128","visible":true},{"fromID":"30_174349664410634128","toID":"26_174349664410634128","visible":true},{"fromID":"30_174349664410634128","toID":"31_174349664410634128","visible":true},{"fromID":"31_174349664410634128","toID":"17_174349664410634128","visible":true},{"fromID":"39_174349664410634128","toID":"38_174349664410634128","visible":false},{"fromID":"40_174349664410634128","toID":"39_174349664410634128","visible":false},{"fromID":"38_174349664410634128","toID":"41_174349664410634128","visible":true},{"fromID":"41_174349664410634128","toID":"37_174349664410634128","visible":true},{"fromID":"43_174349664410634128","toID":"42_174349664410634128","visible":false},{"fromID":"44_174349664410634128","toID":"43_174349664410634128","visible":false},{"fromID":"42_174349664410634128","toID":"45_174349664410634128","visible":true},{"fromID":"45_174349664410634128","toID":"38_174349664410634128","visible":true},{"fromID":"7_174349664410634128","toID":"46_174349664410634128","visible":true},{"fromID":"46_174349664410634128","toID":"42_174349664410634128","visible":true},{"fromID":"49_174349664410634128","toID":"48_174349664410634128","visible":false},{"fromID":"50_174349664410634128","toID":"49_174349664410634128","visible":false},{"fromID":"48_174349664410634128","toID":"51_174349664410634128","visible":true},{"fromID":"51_174349664410634128","toID":"47_174349664410634128","visible":true},{"fromID":"37_174349664410634128","toID":"52_174349664410634128","visible":true},{"fromID":"52_174349664410634128","toID":"47_174349664410634128","visible":true},{"fromID":"42_174349664410634128","toID":"53_174349664410634128","visible":true},{"fromID":"53_174349664410634128","toID":"48_174349664410634128","visible":true},{"fromID":"53_174349664410634128","toID":"54_174349664410634128","visible":true},{"fromID":"54_174349664410634128","toID":"52_174349664410634128","visible":true},{"fromID":"57_174349664410634128","toID":"56_174349664410634128","visible":false},{"fromID":"58_174349664410634128","toID":"57_174349664410634128","visible":false},{"fromID":"48_174349664410634128","toID":"60_174349664410634128","visible":true},{"fromID":"60_174349664410634128","toID":"56_174349664410634128","visible":true},{"fromID":"60_174349664410634128","toID":"61_174349664410634128","visible":true},{"fromID":"61_174349664410634128","toID":"47_174349664410634128","visible":true}]}}